ad_freiburg_qgram_utils-0.4.0.dist-info/METADATA
ad_freiburg_qgram_utils-0.4.0.dist-info/WHEEL
ad_freiburg_qgram_utils-0.4.0.dist-info/license_files/LICENSE
ad_freiburg_qgram_utils/__init__.py
ad_freiburg_qgram_utils/__init__.pyi
ad_freiburg_qgram_utils/py.typed
ad_freiburg_qgram_utils/ad_freiburg_qgram_utils.abi3.so
ad_freiburg_qgram_utils-0.4.0.dist-info/RECORD
