Metadata-Version: 2.3
Name: ad-freiburg-qgram-utils
Version: 0.4.0
Classifier: Programming Language :: Rust
Classifier: Programming Language :: Python :: 3
Classifier: Topic :: Software Development :: Libraries
Classifier: Topic :: Text Processing
Classifier: Topic :: Utilities
License-File: LICENSE
Summary: Rust utilities for q-gram index
Keywords: utilities,index,q-gram
Author-email: Sebastian Walter <swalter@cs.uni-freiburg.de>
Requires-Python: >=3.10
Project-URL: Github, https://github.com/ad-freiburg/qgram-utils
